libtpu/__init__.py
libtpu/libtpu.so
libtpu/sdk.so
libtpu-0.10.0.dist-info/METADATA
libtpu-0.10.0.dist-info/WHEEL
libtpu-0.10.0.dist-info/top_level.txt
libtpu-0.10.0.dist-info/RECORD
