Metadata-Version: 2.2
Name: libtpu
Version: 0.10.0
Summary: Wrapper for the libtpu library.
Author: Google, Inc.
Dynamic: author
Dynamic: description
Dynamic: summary
